gmsnburr/__init__.py
gmsnburr/adjustment.py
gmsnburr/distribution.py
gmsnburr/functions.py
gmsnburr-0.2.0.dist-info/LICENSE
gmsnburr-0.2.0.dist-info/METADATA
gmsnburr-0.2.0.dist-info/WHEEL
gmsnburr-0.2.0.dist-info/top_level.txt
gmsnburr-0.2.0.dist-info/RECORD
