Metadata-Version: 2.2
Name: gmsnburr
Version: 0.2.0
Summary: Distribusi GMSN-Burr dengan PyMC
Home-page: https://github.com/username/gmsnburr
Author: Ezra Zia Izdihara
Author-email: ezrazia05@gmail.com
Classifier: Programming Language :: Python :: 3
Classifier: License :: OSI Approved :: MIT License
Classifier: Operating System :: OS Independent
Requires-Python: >=3.7
License-File: LICENSE
Requires-Dist: numpy
Requires-Dist: pandas
Requires-Dist: pymc
Requires-Dist: pytensor
Requires-Dist: arviz
Requires-Dist: scipy
Requires-Dist: matplotlib
Dynamic: author
Dynamic: author-email
Dynamic: classifier
Dynamic: description
Dynamic: description-content-type
Dynamic: home-page
Dynamic: requires-dist
Dynamic: requires-python
Dynamic: summary
